README.rst
setup.py
mico/__init__.py
mico/decorators.py
mico/environ.py
mico/fifo.py
mico/hook.py
mico/output.py
mico/template.py
mico.egg-info/PKG-INFO
mico.egg-info/SOURCES.txt
mico.egg-info/dependency_links.txt
mico.egg-info/entry_points.txt
mico.egg-info/requires.txt
mico.egg-info/top_level.txt
mico/lib/__init__.py
mico/lib/aws/__init__.py
mico/lib/aws/iam.py
mico/lib/aws/r53.py
mico/lib/aws/ec2/__init__.py
mico/lib/aws/ec2/autoscale.py
mico/lib/aws/ec2/cw.py
mico/lib/aws/ec2/ebs.py
mico/lib/aws/ec2/eip.py
mico/lib/aws/ec2/elb.py
mico/lib/aws/ec2/sg.py
mico/lib/core/__init__.py
mico/lib/core/dir.py
mico/lib/core/file.py
mico/lib/core/group.py
mico/lib/core/local.py
mico/lib/core/network.py
mico/lib/core/service.py
mico/lib/core/ssh.py
mico/lib/core/sudo.py
mico/lib/core/ulimit.py
mico/lib/core/user.py
mico/lib/core/virtualenv.py
mico/lib/core/package/__init__.py
mico/lib/core/package/apt.py
mico/lib/core/package/yum.py
mico/scripts/__init__.py
mico/scripts/cmdline.py
mico/templates/__init__.py
mico/templates/ls.py
mico/util/__init__.py
mico/util/dicts.py
mico/util/mutex.py
mico/util/storage.py
mico/util/switch.py