Metadata-Version: 1.1
Name: mico
Version: 0.1
Summary: A monkey driven cloud management
Home-page: http://ajdiaz.github.com/mico
Author: Andres J. Diaz
Author-email: ajdiaz@connectical.com
License: GPL
Platform: UNKNOWN
Classifier: Development Status :: 4 - Beta
Classifier: Intended Audience :: Developers
Classifier: Natural Language :: English
Classifier: License :: OSI Approved :: GNU General Public License (GPL)
Classifier: Programming Language :: Python :: 2.7
Classifier: Programming Language :: Python :: 2.6
Classifier: Operating System :: OS Independent
Classifier: Programming Language :: Python
